{
  "id": "2.6",
  "category": "Electrical",
  "title": "BURN MARK AT THE CIRCUIT BREAKER",
  "content": "Section 2.6: BURN MARK AT THE CIRCUIT BREAKER\n\nOBSERVATION:\nIt was noted that one of the circuit breakers has an obvious burn mark.\n\nRECOMMENDATION:\nBurn marks on a circuit breaker indicate electrical problems within the system. They are \nthe result of localized overheating within the breaker panel or box. Typically, these marks \noccur due to loose or corroded components and connections, which introduce resistance \nand cause excessive heat generation. Burn marks aren’t just a cosmetic issue; they are a \nwarning of impending danger. These marks can be a precursor to electrical shorts, \npotentially leading to electrical fires or even electric shocks if left unattended.  \nAs such, it is recommended that the circuit breaker:  \n \n1. Tighten all wire connections  to the circuit breaker. Loose electrical connections \nat the breaker or on the wires connected to it can create resistance. This \nresistance in the circuit leads to heat buildup, which can cause burning or charring \nat the connection points.  \n2. Replace faulty breakers  with new, properly rated ones. A malfunctioning or aged \ncircuit breaker might fail to trip during an overload or short circuit, causing heat to \naccumulate and burn marks to appear.  \n3. Investigate the circuit  to identify and fix any short circuits. This may involve \nchecking wiring and outlets for faults, replacing damaged wires, or inspecting \nappliances that may have caused the short. A large current surge can generate \nsignificant heat, causing the circuit breaker to overheat and resulting in burn marks \nor charring around the breaker area.  \n4. Ensure that the total electrical load  on the circuit does not exceed the breaker’s \nrating. If necessary, redistribute the load across other circuits or upgrade to a \nhigher -rated breaker. An overloaded circuit occurs when too many electrical \ndevices or appliances are connected to the same circuit, drawing more current \nthan the breaker is rated for.\n\nREGULATION/GUIDELINE:\nSuruhanjaya Tenaga (Energy Commission) and Malaysian Standards (MS) provide \ncomprehensive guidelines and regulations that cover electrical safety, including \naddressing issues like overloaded circuits, damaged circuit breakers, and burn marks at \ncircuit breakers. These regulations aim to ensure that electrical systems are safe and \nreliable, preventing hazards such as fires, electric shocks, and electrical failures.  \n \n1. Suruhanjaya Tenaga (Energy Commission) Guidelines – Guidelines for \nElectrical Installations (GEI)   \nThe GEI is based on and is a part of the Electricity Supply Act 1990  and the Electricity \nRegulations 1994 . These pieces of legislation set out the legal framework within which \nelectrical installations in Malaysia must be carried out. The GEI issued by Suruhanjaya \nTenaga provides detailed instructions on how electrical systems, including circuit breakers, \nshould be installed, maintained, and inspected:  \n• Circuit Breakers & Overload Protection: Circuit breakers should be correctly sized \naccording to the load requirements and should protect the system from overloads \nor short circuits. If the breaker is under -sized for the circuit, it will not trip properly \nduring an overload or short circuit, which may lead to overheating or burn marks.  \n• Faulty Circuit Breaker Protection: If a circuit breaker shows signs of burning or \ncharring, it could be a sign that it is faulty or that there has been a prolonged \novercurrent event. The guidelines recommend replacing faulty breakers \nimmediately to maintain safety and to avoid electrical fires.  \n• Inspection & Testing: The Energy Commission mandates regular inspections of \nelectrical installations, including breakers, to ensure that they are functioning \nproperly and are safe to use.  \n \n2. MS 1933: 2015 – Code of Practice for the Electrical Wiring of Buildings  \nThis standard outlines  the requirements for electrical wiring in buildings, including the \nproper installation of circuit breakers:  \n• Proper Sizing of Circuit Breakers: MS 1933 emphasizes the importance of \ncorrectly sizing the circuit breakers based on the wire gauge and expected load to \nprevent overheating, overloading, or tripping issues.  \n• Exposed Wires and Circuit Breaker Protection: In the case of burn marks, this \nstandard recommends ensuring that all circuit breakers are protected from \nenvironmental damage (e.g., water, heat) and that exposed wiring is securely \nmounted and insulated.  \n \n3. MS IEC 60364 – Electrical Installations of Buildings  \nThis standard is based on the International Electrotechnical Commission (IEC 60364) and \noutlines safety requirements for electrical installations:  \n• Overload Protection: MS IEC 60364 mandates that circuit breakers must be sized \nappropriately to protect against both overloads and short circuits. If a breaker is too \nsmall for the circuit or too large to trip in time, it can cause serious issues such as \noverheating and burn marks.  \n• Electrical Faults & Protection: The standard provides detailed requirements on the \nprotection devices such as circuit breakers, fuses, and earth leakage circuit \nbreakers (ELCBs), which must be installed to prevent fire risks due to overheating \nof wiring or failure of the circuit protection devices.  \n \n4. MS 1571: 2016 – Electrical Installation Safety Standards  \nThis standard covers the general safety requirements for electrical installations, including \nprotection against electrical faults that could lead to burn marks:  \n• Circuit Breaker Safety: MS 1571 stipulates that circuit breakers should be installed \nand maintained in accordance with the manufacturer’s instructions. The breaker \nmust be designed to protect against overcurrent and fault conditions, and if it fails \nto do so, it should be replaced immediately.  \n• Routine Maintenance: Regular maintenance and inspections are mandated to \nensure that the circuit breaker and entire electrical system function safely. Any \nsigns of burn marks or damage should be inspected by a qualified professional \nand repaired promptly.",
  "token_count": 1512,
  "metadata": {
    "section_number": "2.6",
    "section_title": "BURN MARK AT THE CIRCUIT BREAKER",
    "category": "Electrical",
    "regulations": [
      "IEC 60364 – Electrical Installations of Buildings",
      "MS 1571: 2016 – Electrical Installation Safety Standards",
      "MS 1933: 2015 – Code of Practice for the Electrical Wiring of Buildings"
    ],
    "keywords": [
      "damage",
      "safety",
      "leakage",
      "electrical",
      "code",
      "fire",
      "failure",
      "regulation",
      "inspection",
      "standard"
    ],
    "risk_type": "fire"
  }
}