{
  "id": "3.1",
  "category": "Housekeeping",
  "title": "FLOOR AREA COVERED WITH GREASE AND GRIME",
  "content": "Section 3.1: FLOOR AREA COVERED WITH GREASE AND GRIME\n\nOBSERVATION:\nMany floors and machinery within the Mill were observed to be covered with grease and \ngrime. This condition not only compromises the cleanliness and overall housekeeping \nstandards but also poses significant safety and operational risks. it may pose  risks as \nfollows:  \n \nSlips, Trips, and Falls:  \n - Greasy floors increase the likelihood of accidents, leading to potential injuries to \npersonnel.  \n \nOperational Inefficiencies:  \n - Greasy machinery may experience reduced efficiency and increased wear and tear, \npotentially leading to mechanical failures and unplanned downtime.  \n \nFire Hazards:  \n - The accumulation of grease and oil can act as a fuel source, increasing the risk of fire, \nespecially in areas where machinery operates at high temperatures.\n\nRECOMMENDATION:\nIt is recommended that the followings:  \n \nThorough Cleaning:  \n - Implement a regular and comprehensive cleaning schedule to remove grease from \nfloors and machinery. Use appropriate cleaning agents and tools suitable for the Millâ€™s \noperations to ensure effective grease removal.  \n \nPreventive Maintenance:  \n - Establish a preventive maintenance program to regularly inspect and clean machinery. \nEnsure that oil leaks or spills from machinery are promptly identified and rectified.  \n \nHousekeeping Standards:  \n - Train staff on the importance of maintaining high housekeeping standards. Introduce \nworkplace cleanliness policies, ensuring that all employees contribute to maintaining a \nclean and safe working environment.  \n \nNon-Slip Flooring:  \n - Consider installing non -slip flooring or mats in high -risk areas to minimize the risk of \nslips and falls.\n\nREGULATION/GUIDELINE:\n1. Occupational Safety and Health Act 1994 (Act 514)  \n \nGeneral Duties of Employers and Self -Employed Persons to Their Employees  (Section \n15) \n- This section mandates that employers and self -employed individuals ensure, as far as \npracticable, the safety, health, and welfare of their employees at work. This includes \nproviding and maintaining a work environment that is safe and without health risks, \nwhich implicitly covers good housekeeping practices  \n \nDuty to Formulate Safety and Health Policy  (Section 16)  \n \nEmployers are required to prepare and revise a written statement of their general policy concerning the safety and health at work of their employees.  \n \nNote: This policy should include arrangements for maintaining a safe working \nenvironment, which would involve proper housekeeping measures",
  "token_count": 640,
  "metadata": {
    "section_number": "3.1",
    "section_title": "FLOOR AREA COVERED WITH GREASE AND GRIME",
    "category": "Housekeeping",
    "regulations": [],
    "keywords": [
      "safety",
      "mechanical",
      "risk",
      "fire",
      "regulation",
      "maintenance"
    ],
    "risk_type": "fire"
  }
}