{
  "id": "3.2",
  "category": "Housekeeping",
  "title": "STORAGE OF UNUSED METAL",
  "content": "Section 3.2: STORAGE OF UNUSED METAL\n\nOBSERVATION:\nUnused metals were observed stored in multiple locations within the premises, including \nthe right side of the Mill. This not only detracts from the overall housekeeping standards \nbut also introduces various safety and operational risks. it may pose  risks as follows:  \n \nObstruction Hazards:  \n - Improperly stored metals can block walkways, create tripping hazards, and hinder \nefficient movement within the Mill.  \n \nFire Risks:  \n - Stacked or scattered metals may become an obstruction during an emergency \nevacuation and, in some cases, may contribute to fire hazards, particularly if stored near \nheat sources.  \n \nInefficient Space Utilization:  \n - Random storage of materials reduces the effective utilization of available space, \nimpacting overall operational efficiency .\n\nRECOMMENDATION:\nIt is recommended that as follows:  \n \nDesignated Storage Areas:  \n - Establish clearly defined storage areas for unused metals, located far from the Mill and \noperational areas. These areas should be secure, organized, and labelled  to facilitate \neasy identification and retrieval of materials.  \n \nRegular Removal of Unused Materials:  \n - Develop a material management policy to regularly remove unused metals from \noperational spaces to designated storage or disposal areas.  \n \nHousekeeping Pro cedure : \n - Enhance housekeeping standards by introducing systematic inspections to identify and \naddress cluttered or improperly stored materials promptly.  \n \nSafety Signage and Training:  \n - Install clear signage to indicate storage rules and provide training to employees on \nproper material handling and storage practices to prevent clutter and ensure safety\n\nREGULATION/GUIDELINE:\n1. Occupational Safety and Health Act 1994 (OSHA 1994)  \n \nGeneral Duties of Employers (Section 15):  \n - Employers are required to ensure the safety, health, and welfare of employees by \nmaintaining a clean and organized workplace.  \n \nNote: Improper storage of materials, such as unused metals, increases risks of tripping, \nobstruction, and potential injuries, violating this duty.  This also related to e stablish \ndesignated storage areas for unused metals aligns with this requirement.  \n \n2. Factories and Machinery (Safety, Health, and Welfare) Regulations 1970  \n \nRegulation 6: Floor  \n- Requires that every part of any floor where any person is likely to pass shall be maintained in a level, good, and non -slippery condition to afford safe walking and, \nwhere necessary, safe trucking or handling of materials.  \n \nNote: This also can be related  that the r equire ments of  all materials, including unused \nmetals, to be stored in an organized manner to prevent hazards such as tripping  and \nfalling. \n \n \nRegulation 7: Access of place of work. : \n- Clear and unobstructed space shall be provided and maintained at all machinery to \nenable any work thereat to be performed without unnecessary risk, and to permit of free \nand ready access to any part necessitating regular operation, inspection, maintenance or \nremoval.  \n- Where materials or goods or other articles are necessarily stacked between any \nmachines or workbenches, clear aisles or gangways to such machines or workbenches \nshall be provided and maintained, and such aisles or gangways shall be clearly marked on \nthe floor and no materials or goods,  or other articles shall be stacked on such aisles or \ngangways.",
  "token_count": 859,
  "metadata": {
    "section_number": "3.2",
    "section_title": "STORAGE OF UNUSED METAL",
    "category": "Housekeeping",
    "regulations": [],
    "keywords": [
      "safety",
      "risk",
      "emergency",
      "fire",
      "regulation",
      "inspection",
      "maintenance"
    ],
    "risk_type": "fire"
  }
}