{
  "id": "4.1",
  "category": "Human Element",
  "title": "FIRE EVACUATION",
  "content": "Section 4.1: FIRE EVACUATION\n\nOBSERVATION:\nFire Evacuation is not adopted in the risk.  \n \nThe absence of a fire evacuation plan at the facility poses significant safety risks to \nemployees, visitors, and assets. A fire evacuation plan is a critical component of \nworkplace safety, designed to ensure that all occupants can exit the premises quickly and \nsafely during an emergency. Failure to implement such a plan not only increases the \nlikelihood of injuries or fatalities during a fire but also exposes the facility to legal, \noperational, and reputational risks.  \n \nRisks Associated with the Absence of a Fire Evacuation Plan:  \n \nIncreased Risk of Injuries or Fatalities:  \n -  Without a structured evacuation plan, occupants may panic or take unsafe actions \nduring a fire, leading to injuries or loss of life.  \n \nOperational and Asset Damage:  \n - Delays in evacuation can result in increased exposure to fire, potentially causing more \nextensive damage to property and critical infrastructure.  \n \nNon-Compliance with Safety Regulations:  \n - The lack of a fire evacuation plan may violate local safety regulations and standards, \nleading to penalties, fines, or operational shutdowns.  \n \nReputational Damage:  \n - Inadequate safety measures can harm the organizationâ€™s reputation, impacting \nemployee morale and public trust.\n\nRECOMMENDATION:\nIt is recommended that a fire evacuation plan be adopted. To address these risks, the \nfollowing recommendations are proposed:  \n \nDevelop a Comprehensive Fire Evacuation Plan:  \nEngage a certified fire safety consultant to design a customized evacuation plan tailored to \nthe facility's layout, occupancy, and operational hazards.  \nInclude detailed evacuation routes, designated assembly points, and procedures for aiding \nindividuals with mobility challenges.  \n \nInstall Appropriate Emergency Signage and Equipment:  \nClearly mark all exit routes with illuminated signs.  \nInstall emergency lighting in critical areas to guide occupants during power outages or low \nvisibility conditions.  \n \nConduct Regular Training and Drills:  \nTrain all employees on evacuation protocols, including the location of exits, assembly \npoints, and fire -fighting equipment.  \nConduct evacuation drills at least bi -annually to reinforce awareness and evaluate plan \neffectiveness.  \n \nAppoint and Train Fire Wardens:  \nDesignate responsible individuals as fire wardens to lead evacuation efforts and assist in \nensuring all occupants are safely evacuated.  \n \nInstall and Maintain Fire Safety Systems:  Equip the facility with functional fire alarms, sprinklers, and extinguishers. Ensure regular \nmaintenance checks.  \n \nDevelop Emergency Communication Protocols:  \nImplement a system to communicate evacuation orders effectively, such as alarms, PA \nannouncements, or mobile notifications.\n\nREGULATION/GUIDELINE:\nIn Malaysia, the implementation of fire evacuation plans is governed by several key \nregulations and guidelines designed to ensure the safety of building occupants during \nemergencies.  \n \n1. Fire Services Act 1988 (Act 341):  \n \nSection 27: Empowers the Director General to designate certain premises as requiring \nspecific fire safety measures, which may include the development and implementation of \nfire evacuation plans.  \n \nSection 28: Mandates that owners or occupiers of designated premises obtain a fire \ncertificate, which necessitates compliance with prescribed fire safety measures, potentially \nencompassing evacuation procedures.  \n \n2. Uniform Building By -Laws 1984 (UBBL 1984):  \n \nBy-Law 225: Requires the formulation of a fire emergency plan for buildings, detailing \nevacuation procedures, escape routes, and the appointment of fire safety managers to \noversee emergency preparedness.  \n \nBy-Law 139: Stipulates that exit routes must be clearly marked and maintained to facilitate \nsafe evacuation during emergencies.  \n \n3. Occupational Safety and Health Act 1994 (OSHA 1994):  \n \nSection 15: Obligates employers to ensure, as far as practicable, the safety, health, and \nwelfare of all employees, which includes establishing effective emergency response plans \nlike fire evacuation procedures.  \n \nSection 16: Mandates the formulation of a safety and health policy, encompassing \nmeasures for dealing with emergencies, including fires.",
  "token_count": 1079,
  "metadata": {
    "section_number": "4.1",
    "section_title": "FIRE EVACUATION",
    "category": "Human Element",
    "regulations": [
      "Section 15: Obligates employers to ensure, as far as practicable, the safety, health, and",
      "OSHA 1994):",
      "Section 27: Empowers the Director General to designate certain premises as requiring",
      "Section 28: Mandates that owners or occupiers of designated premises obtain a fire",
      "Section 16: Mandates the formulation of a safety and health policy, encompassing"
    ],
    "keywords": [
      "damage",
      "safety",
      "risk",
      "emergency",
      "fire",
      "failure",
      "compliance",
      "regulation",
      "maintenance"
    ],
    "risk_type": "fire"
  }
}