{
  "id": "4.8",
  "category": "Human Element",
  "title": "SAFETY COMMITTEE",
  "content": "Section 4.8: SAFETY COMMITTEE\n\nOBSERVATION:\nA well -structured Safety and Health Committee (SHC) is critical to ensuring workplace \nsafety, legal compliance, and a proactive approach to occupational hazards. Given that \ninsured  employs more than 40 personnel, it is a mandatory requirement under Regulation \n30 of the Occupational Safety and Health Act (OSHA) 1994 that a Safety Committee be \nestablished.\n\nRECOMMENDATION:\nA properly functioning safety committee helps to:  \n \n- Ensure compliance with occupational health and safety laws.  \n- Prevent workplace accidents through hazard identification and mitigation.  \n- Improve workplace safety culture by fostering communication between employees \nand management.  \n- Reduce financial and reputational risks arising from workplace accidents, injuries, \nand legal penalties.  \n- Provide a structured response in the event of an emergency or accident.  \n \nTo mitigate safety risks and ensure compliance, it is strongly recommended that insured:  \n \n1. Establish a Safety Committee Immediately  \n- Form a dedicated Safety and Health Committee (SHC) comprising employer \nrepresentatives, management, and employee representatives.  \n- Assign a Chairperson, Secretary, and Committee Members with clear roles and \nresponsibilities.  \n- Conduct an inaugural safety meeting to set objectives, review past incidents, and \ndiscuss safety policies.  \n \n2. Conduct Regular Safety Meetings & Inspections  \n- Hold quarterly safety meetings (at least once every three months) to review workplace \nhazards, near misses, and safety improvements.  \n- Carry out comprehensive safety inspections every three months to assess compliance \nwith OSHA\n\nREGULATION/GUIDELINE:\nThe establishment and operation of a Safety Committee must comply with the following \nlegal provisions:  \n 1. Occupational Safety and Health Act (OSHA) 1994 (Act 514)  \nSection 30: Requires employers with more than 40 employees to form a Safety and Health \nCommittee.  \nSection 15: Employers have a duty to ensure the safety, health, and welfare of employees.  \nSection 24: Employees must take reasonable care for their own safety and cooperate with \nsafety measures implemented by their employer.  \n \n2. Occupational Safety and Health (Safety and Health Committee) Regulations \n1996  \nRegulation 6(1): A Safety and Health Committee must be established if the workplace has \nmore than 40 employees.  \nRegulation 21: The Safety Committee must meet at least once every three months.  \nRegulation 12: A comprehensive workplace safety inspection must be conducted every \nthree months to identify hazards.  \nRegulation 18: Minutes of safety committee meetings must be kept for at least seven \nyears.  \nRegulation 22: Employers must report any workplace accidents, near misses, or \ndangerous occurrences to the Department of Occupational Safety and Health (DOSH).",
  "token_count": 714,
  "metadata": {
    "section_number": "4.8",
    "section_title": "SAFETY COMMITTEE",
    "category": "Human Element",
    "regulations": [
      "Section 24: Employees must take reasonable care for their own safety and cooperate with",
      "Section 30: Requires employers with more than 40 employees to form a Safety and Health",
      "Section 15: Employers have a duty to ensure the safety, health, and welfare of employees."
    ],
    "keywords": [
      "safety",
      "hazard",
      "risk",
      "emergency",
      "compliance",
      "regulation",
      "inspection"
    ],
    "risk_type": "safety"
  }
}