{
  "id": "5.10",
  "category": "Process",
  "title": "WEIR INTEGRITY TESTING",
  "content": "Section 5.10: WEIR INTEGRITY TESTING\n\nOBSERVATION:\nCurrently, weir inspection and integrity testing are not conducted as part of preventive \nmaintenance for mini hydroelectric.\n\nRECOMMENDATION:\nWeirs require regular integrity testing as part of maintenance and safety protocols to \nensure structural stability and hydraulic efficiency. A weir, constructed across a river or \nstream to regulate water flow or raise water levels, is a critical component of flood control, \nflow measurement, and water management infrastructure.  \n \nAs such, an integrity testing should be incorporated into the preventive maintenance \nprogram for the mini hydroelectric.  Integrity testing should include detailed structural \ninspections to identify cracks, deformation, and material degradation using visual methods \nand non -destructive testing (NDT) techniques such as ultrasonic testing (UT) and acoustic \nemission testing (AET) to detect internal defects and voids. Seepage monitoring should be \nconducted using piezometers to measure pore water pressure and identify seepage paths \nthrough the structure or foundation. Dye tracing can be employed to map leakage patterns \nand identify failure points. Hydraulic performance evaluation should involve stage -\ndischarge analysis and flow rating measurements to confirm the weir's discharge capacity \nunder varying hydraulic loads. Sedimentation surveys using sonar or echo sounders \nshould be performed to monitor sediment accumulation that could reduce flow efficiency. \nErosion monitoring should include scour depth measurements and geotechnical \nassessments at the crest, spillway, and downstream apron to detect undercutting and soil \ninstability. For mechanically operated weirs, functional testing of gates, valves, and \nactuators should be performed, including load testing, torque measurements, and \nalignment verification. Structural health monitoring (SHM) systems incorporating \npiezometers, tiltmeters, and strain gauges should be installed for real -time monitoring of \ndisplacement, settlement, and structural response under hydraulic loading. These \ncomprehensive testing measures ensure that the weir maintains operational integrity and \nstructural resilience under dynamic flow conditions.\n\nREGULATION/GUIDELINE:\nWeirs are considered important hydraulic structures, and although there are no specific \nstandards exclusively dedicated to weir integrity testing, several general standards and \nguidelines related to water control structures can be applied. These standards mainly \nfocus on aspects like structural integrity, hydraulic performance, and safety for all types of \nwater -related infrastructure, including dams, weirs, and spillways. Below are key \nstandards and guidelines that can be relevant for weir integrity testing in Malaysia:  \n \n1. Malaysian Standard (MS) 1195:2011 - Code of Practice for Earthworks in the \nUrban Environment  \nWhile this standard is mainly for earthworks, it also applies to structures like weirs, which \noften involve embankment and earth -fill construction. The standard outlines requirements \nfor construction quality, material testing, and monitoring of earthworks, which can be \nuseful when considering the foundations of a weir.  \nRelevant Sections:  \n• Soil Compaction and Material Integrity: MS 1195 specifies methods for soil \ncompaction and the required quality of materials used in the embankment, which is \ncrucial for the stability of weirs that rely on earth materials.  • Settlement Monitoring:  The standard recommends practices for settlement \nmonitoring that can be applied to monitor shifts or deformations in the earth \nstructures around weirs.  \n \n2. MS ISO 9001:2015 - Quality Management Systems  \nAlthough this is a general standard for quality management systems, its principles can be \napplied to the maintenance and integrity testing of weirs. MS ISO 9001 emphasizes \ncontinual improvement and risk management, both of which are critical when assessing \nthe safety and performance of hydraulic structures.  \nRelevant Sections:  \n• Inspection and Monitoring: Under MS ISO 9001, weir operators are required to \ninspect and monitor the performance of the structure, including aspects such as \nseepage, structural deformations, and hydraulic efficiency.  \n• Documenting Maintenance Activities: The standard mandates that inspections and \nintegrity tests be well -documented and traceable, ensuring accountability for the \ntesting and maintenance processes.  \n \n3. Malaysian Code of Practice for Structural Use of Concrete (MS 523:2005)  \nThis code of practice covers the design and construction of concrete structures, including \nweirs, particularly concrete weirs and spillways. It provides guidelines for structural \nintegrity testing of concrete components, which is a crucial aspect of weir safety.  \nRelevant Sections:  \n• Concrete Quality and Testing: The standard outlines the requirements for testing \nthe quality of concrete, such as compressive strength, crack resistance, and \nwatertightness. This applies to the weir structure itself, especially if it’s made of \nreinforced concrete.  \n• Inspection and Monitoring: MS 523 specifies methods for the visual inspection and \nNDT (non -destructive testing) of concrete surfaces to detect cracks or defects in \nthe structure.  \n \n4. Jabatan Pengairan dan Saliran (JPS) Guidelines  \nJPS (Department of Irrigation and Drainage) under the Ministry of Water, Land, and \nNatural Resources provides guidelines for water resources management, including the \ndesign, construction, and maintenance of weirs and similar structures.  \nKey Aspects:  \n• Maintenance and Inspection Protocols: JPS guidelines provide general protocols \nfor regular maintenance and safety inspections of hydraulic structures, including \nweirs. This involves both visual inspections and more advanced instrumental \nmonitoring.  \n• Seepage and Erosion Control: JPS guidelines specifically focus on the prevention \nof seepage and erosion, which are critical to the safety of weirs.  \n• Hydraulic Performance Monitoring: JPS also emphasizes the need to regularly \ncheck hydraulic performance, including flow measurement and ensuring that the \nweir is functioning within the expected range.  \n \n5. International Commission on Large Dams (ICOLD) Guidelines  \nThe ICOLD provides best practices and guidelines for dam safety that can be applied to \nsimilar hydraulic structures, such as weirs. ICOLD guidelines emphasize the need for \nsafety assessments, regular testing, and monitoring of water -retaining structures.  \nKey Areas in ICOLD Guidelines:  \n• Safety Assessments: ICOLD emphasizes that a safety assessment of a weir \nshould include structural testing, hydraulic evaluations, and seepage monitoring.  • Monitoring and Maintenance: ICOLD guidelines suggest implementing a \nmonitoring system that tracks the performance of the weir, particularly during high -\nflow events or significant weather changes.  \n \n6. Malaysian Standard (MS 2446:2012) - Design and Installation of Embedded \nGround Instrumentation  \nThis standard focuses on the design and installation of instrumentation to monitor the \nintegrity of structures, including weirs. It covers the use of various geotechnical \ninstruments to monitor stress, strain, and displacement in the soil and structure.  \nRelevant Sections:  \n• Piezometers: This standard provides guidelines for the installation of piezometers \nto measure pore water pressure, which is crucial for monitoring seepage in weir \nfoundations and surrounding areas.  \n• Inclinometers and Displacement Monitoring: It also outlines how inclinometers and \nother instruments can be used to measure displacement and detect deformations \nin the structure over time.  \n \n7. The Manual for Safety of Dams (JPS Guidelines)  \nThe JPS Manual for Safety of Dams is a comprehensive document that provides safety \nguidelines for all types of dams and water management structures, including weirs. While \nmore focused on larger dams, many of the safety principles apply to weirs as well.  \nKey Guidelines:  \n• Regular Inspections and Testing: The manual mandates that safety and integrity \ninspections of weirs should be conducted on a regular basis and whenever \nsignificant changes occur (e.g., after floods).  \n• Hydrological Monitoring: It also suggests ongoing hydrological assessments to \nensure that water levels are controlled and that the structure can handle high -\nwater events.  \n• Failure Modes and Risk Assessments: The manual emphasizes the importance of \nperforming failure mode analyses and risk assessments to predict potential \nproblems and take pre -emptive action.  \n \n8. Department of Irrigation and Drainage (DID) - Guidelines for Hydrological and \nHydraulic Design of Weirs  \nThis set o f guidelines from the Department of Irrigation and Drainage (DID) provides best \npractices for the design and hydraulic performance of weirs, ensuring that they meet \nsafety requirements.  \nKey Areas:  \n• Flow Capacity and Performance Tests: The guidelines emphasize regular flow \ncapacity tests to ensure that the weir is functioning correctly and not obstructing \nwater flow.  \n• Seepage and Erosion: Specific guidelines are given for monitoring seepage \naround the weir structure and taking corrective measures for any signs of erosion \nor degradation.",
  "token_count": 2327,
  "metadata": {
    "section_number": "5.10",
    "section_title": "WEIR INTEGRITY TESTING",
    "category": "Process",
    "regulations": [],
    "keywords": [
      "safety",
      "leakage",
      "risk",
      "code",
      "failure",
      "monitoring",
      "structural",
      "inspection",
      "regulation",
      "standard"
    ],
    "risk_type": "electrical"
  }
}