{
  "id": "5.8",
  "category": "Process",
  "title": "TEMPERATURE MONITORING FOR PALM KERNEL STORAGE",
  "content": "Section 5.8: TEMPERATURE MONITORING FOR PALM KERNEL STORAGE\n\nOBSERVATION:\nThe risk is provided with two units of palm kernel silos, and sometimes the palm kernel is \nstored in the warehouse during peak production periods. It was noted that both the kernel \nsilo and pile storage are not equipped with temperature monitoring.\n\nRECOMMENDATION:\nPalm kernels, though not as volatile as crude palm oil, can still pose a fire risk under \ncertain conditions. Some of the factors contributing to fire risks in palm kernel storage are:  \n \n• Oily nature of palm kernels: The kernels contain natural oils, which are flammable \nunder the right conditions, especially when exposed to high temperatures or \nimproper storage conditions.  \n• Dust accumulation: The dust generated from processing palm kernels can be \nhighly flammable and pose an explosion risk when mixed with air.  \n• Spontaneous combustion: Spontaneous combustion can occur if palm kernels or \nother organic materials like fibre are stored in poorly ventilated conditions. The \ninternal heat generated from biological decomposition or oxidation of the oil may \nlead to a fire.  \n \nTo mitigate the risk of fire hazards and spontaneous combustion, it is recommended to \ninstall a comprehensive temperature monitoring system for both palm kernel silos and pile \nstorage. Palm kernels are prone to spontaneous combustion due to their oily nature and \nthe buildup of heat from biological activity and oxidation. Installing continuous temperature \nmonitoring with sensors placed at multiple levels within the silo and across different areas \nof the pile storage will help detect abnormal temperature increases early. High -\ntemperature alarms should be integrated with the plant's control system to trigger an \nautomatic response if temperatures exceed safe limits (typically 45°C to 50°C). The \nmonitoring system should provide real -time data logging and remote access to allow for \nquick intervention. Regular calibration and maintenance of the sensors should be included \nin the maintenance program to ensure accuracy and reliability. Implementing this system \nwill improve safety, prevent product loss, and enhance overall operational efficiency\n\nREGULATION/GUIDELINE:\n1. MSPO (Malaysian Sustainable Palm Oil) Standard  \nThe MSPO certification is the national standard for sustainable palm oil production in \nMalaysia. It ensures that palm oil production complies with environmental, social, and \neconomic criteria. While MSPO does not explicitly require temperature monitoring for \npalm kernel storage , it emphasizes the importance of good agricultural practices  \n(GAP) and overall sustainability, which includes proper handling and storage of palm \nproducts.  \n \nRelevant MSPO Principles and Criteria Related to Temperature Monitoring  \n• Principle 3: Social Responsibility, Health, Safety, and Employment  \no MSPO emphasizes the health and safety of workers, which can include \nensuring that palm oil storage conditions are safe and that the environment \naround the storage is non -hazardous. Proper temperature control in \nstorage areas is one way to ensure the safety and quality of stored palm \nkernels, as poorly controlled temperature can lead to spoilage or \ncontamination that may compromise worker safety.  \n• Principle 4: Environmental Responsibility and Conservation of Natural Resources  and Biodiversity   \no This principle stresses the need for responsible environmental practices \nthat prevent harm to natural resources. In the context of palm kernel \nstorage, environmental responsibility would include maintaining proper \ntemperature control to prevent spoilage or decomposition, which could lead \nto waste, environmental contamination, or unnecessary disposal of \nproducts.  \n• Principle 5: Best Practices  \no MSPO stresses the importance of following best practices throughout the \nproduction and processing phases, including the storage of palm products. \nTemperature control would be considered part of these best practices in the \nhandling and storage of palm kernels to ensure that the product remains of \nhigh quality.  \n• Traceability and Record -Keeping:  \no MSPO requires producers to maintain records that demonstrate traceability \nof the palm oil products from farm to mill and ultimately to the consumer. \nThis includes ensuring that palm kernels are stored in a controlled \nenvironment. Monitoring temperature in the storage process could form \npart of the documentation and record -keeping practices, which ensures that \npalm kernels are stored at appropriate conditions throughout the entire \nsupply chain.  \n \nMSPO Guidelines on Storage Conditions  \n• While MSPO does not have a dedicated temperature monitoring requirement for \npalm kernel storage, it does require proper storage conditions to avoid \ndegradation. Storing palm kernels at proper temperatures (around 25 -30°C) is \nessential to preserve their quality and prevent rancidity, mold growth, or insect \ninfestations.  \n• For sustainability, palm oil processors must ensure that storage practices do not \nnegatively impact the environment. Ventilated storage areas and appropriate \ntemperature monitoring systems help mitigate negative impacts such as spoilage \nor unnecessary waste.  \n \n2. RSPO (Roundtable on Sustainable Palm Oil) Standard  \nThe RSPO  is an international certification system that promotes the production and use of \nsustainable palm oil. It sets criteria for environmental, social, and economic sustainability, \nincluding the handling, storage, and transportation of palm oil products. Like MSPO, \nRSPO does not explicitly mandate temperature monitoring for palm kernel storage, but it \nemphasizes good manufacturing practices (GMP) and the maintenance of quality \nthroughout the supply chain.  \nRelevant RSPO Principles and Criteria Related to Temperature Monitoring  \n \n• Principle 4: Use of Appropriate Best Practices by Growers and Millers  \no RSPO requires that palm oil mills and storage facilities implement best \npractices for palm oil production and processing. This includes the handling \nand storage of palm oil products such as palm kernels. Temperature control \nis considered part of good practice because it ensures that palm kernels do \nnot spoil or degrade, preserving the quality and sustainability of the \nproduct.  \n• Principle 5: Environmental Responsibility and Conservation of Natural Resources \nand Biodiversity  \no RSPO requires that palm oil producers minimize waste and optimize resource use. Proper storage conditions —such as maintaining the right \ntemperature for palm kernels —help reduce spoilage, waste, and loss of \nproduct. This aligns with the RSPO's commitment to reducing \nenvironmental impact and optimizing the use of natural resources in palm \noil production.  \n• Principle 7: Responsible Development of New Plantings  \no RSPO certification ensures traceability throughout the palm oil supply \nchain, which includes monitoring the quality and storage conditions of \nproducts. Proper temperature control is one aspect of ensuring traceability, \nas maintaining product quality during storage is essential for ensuring that it \nmeets the sustainability and quality criteria required for RSPO certification.  \n \nRSPO Guidelines on Storage Conditions and Temperature Control  \n• Temperature control is part of the good manufacturing practices (GMP ) that RSPO \npromotes. The guidelines emphasize the importance of ventilation, cooling, and \nproper handling of palm oil products, including palm kernels, to ensure they remain \nin good condition.  \n• Best practices for palm kernel storage include:  \no Ensuring cool and dry storage conditions to prevent oxidation, fungal \ngrowth, or insect infestations.  \no Monitoring the temperature and humidity of storage areas to ensure the \nproduct is maintained within the ideal range (typically 25 -30°C for palm \nkernels) to avoid spoilage.  \n• Traceability is another key element in the RSPO certification process. The \nstandard encourages the monitoring and documentation of storage conditions, \nincluding temperature logging, to ensure that products are stored correctly, and \ntheir quality is maintained from the point of production to distribution.  \n \n3. Industry Best Practices for Temperature Control in Palm Kernel Storage  \nWhile MSPO and RSPO do not mandate temperature monitoring in detail for palm kernel \nstorage, industry best practices are often followed in compliance with the broader \nsustainability and quality guidelines provided by these certifications. Some of these best \npractices include:  \n• Temperature Range:  \no Palm kernels should ideally be stored at ambient temperatures between \n25-30°C. If stored at higher temperatures, kernels may undergo oxidation, \nleading to rancidity and quality loss.  \n• Ventilated Storage:  \no Proper ventilation is critical in controlling both temperature and humidity. \nPoor ventilation can lead to moisture buildup, which increases the risk of \nmold growth and spoilage.  \n• Temperature Monitoring Systems:  \no Automated temperature control systems and monitoring devices are \nincreasingly used in storage facilities. These systems include sensors to \ntrack temperature fluctuations and alarms to signal when temperatures fall \noutside acceptable ranges.  \n• Regular Monitoring and Record Keeping:  \no Temperature logs are often maintained as part of traceability efforts. These \nlogs record the temperature conditions of storage areas at regular intervals \nand help ensure compliance with sustainability standards and industry \nnorms.  \n• Monitoring of Humidity:  o In addition to temperature, humidity is another critical factor in palm kernel \nstorage. High humidity can lead to mold  growth and fungal contamination. \nProper moisture control can prevent the kernels from degrading and ensure \nthey remain in good condition.",
  "token_count": 2459,
  "metadata": {
    "section_number": "5.8",
    "section_title": "TEMPERATURE MONITORING FOR PALM KERNEL STORAGE",
    "category": "Process",
    "regulations": [],
    "keywords": [
      "safety",
      "explosion",
      "risk",
      "fire",
      "compliance",
      "monitoring",
      "regulation",
      "standard",
      "maintenance"
    ],
    "risk_type": "fire"
  }
}